pyqubit/__init__.py
pyqubit-0.3.1.dist-info/LICENSE
pyqubit-0.3.1.dist-info/METADATA
pyqubit-0.3.1.dist-info/WHEEL
pyqubit-0.3.1.dist-info/top_level.txt
pyqubit-0.3.1.dist-info/RECORD
