Metadata-Version: 2.1
Name: pyqubit
Version: 0.3.1
Summary: A lightweight quantum qubit simulator in Python
Home-page: https://github.com/yourusername/PyQubit
Author: Aviral Srivastava
Author-email: your_email@example.com
Classifier: Programming Language :: Python :: 3
Classifier: License :: OSI Approved :: MIT License
Classifier: Operating System :: OS Independent
Requires-Python: >=3.6
License-File: LICENSE
